py_variety/__init__.py
py_variety/formal_fields.py
py_variety-0.1.0.dist-info/LICENSE
py_variety-0.1.0.dist-info/METADATA
py_variety-0.1.0.dist-info/WHEEL
py_variety-0.1.0.dist-info/top_level.txt
py_variety-0.1.0.dist-info/RECORD
