Metadata-Version: 2.1
Name: py-variety
Version: 0.1.0
Summary: Use variety by python.
Home-page: https://github.com/LZC6244/py_variety
Author: maida
Author-email: 624486877@qq.com
License: UNKNOWN
Platform: UNKNOWN
Classifier: Programming Language :: Python :: 3
Classifier: License :: OSI Approved :: MIT License
Classifier: Operating System :: OS Independent
Requires-Dist: pymongo
